ons_sds_publisher_demo/__init__.py
ons_sds_publisher_demo/publisher_service.py
ons_sds_publisher_demo-0.0.2.dist-info/LICENSE
ons_sds_publisher_demo-0.0.2.dist-info/METADATA
ons_sds_publisher_demo-0.0.2.dist-info/WHEEL
ons_sds_publisher_demo-0.0.2.dist-info/top_level.txt
ons_sds_publisher_demo-0.0.2.dist-info/RECORD
